confluence_cli/cli/__init__.py
confluence_cli/cli/comala_api.py
confluence_cli/cli/confluence_async.py
confluence_cli/cli/confluence_limited.py
confluence_cli/cli/confluence_wrapper.py
confluence_cli/cli/iterators.py
confluence_cli/cli/paginators.py
confluence_cli/cli/types.py
confluence_cli/cli/utils.py
confluence_cli-0.9.0.dist-info/METADATA
confluence_cli-0.9.0.dist-info/WHEEL
confluence_cli-0.9.0.dist-info/licenses/LICENSE.txt
confluence_cli-0.9.0.dist-info/RECORD
