Metadata-Version: 2.4
Name: confluence-cli
Version: 0.9.0
Summary: Just another Atlassian Confluence API cli extension
Author-email: "J. Andres Guerrero" <juguerre@gmail.com>
License-Expression: MIT
License-File: LICENSE.txt
Requires-Python: <3.13,>=3.9.0
Requires-Dist: aiohttp<4,>=3
Requires-Dist: aiologger<1,>=0
Requires-Dist: atlassian-python-api<3.24,>=3.23
Requires-Dist: click-completion<1,>=0
Requires-Dist: click<9,>=8
Requires-Dist: coloredlogs<16,>=15
Requires-Dist: python-box<7,>=6
Requires-Dist: python-decouple<4,>=3
Requires-Dist: python-dotenv
Requires-Dist: pyyaml<7,>=6
Requires-Dist: requests<3,>=2
Requires-Dist: tqdm<5,>=4
Requires-Dist: urllib3<2,>=1
